ikpls/__init__.py
ikpls/fast_cross_validation/__init__.py
ikpls/fast_cross_validation/numpy_ikpls.py
ikpls/jax_ikpls_alg_1.py
ikpls/jax_ikpls_alg_2.py
ikpls/jax_ikpls_base.py
ikpls/numpy_ikpls.py
ikpls-4.0.1.dist-info/METADATA
ikpls-4.0.1.dist-info/WHEEL
ikpls-4.0.1.dist-info/licenses/LICENSE
ikpls-4.0.1.dist-info/RECORD
