Metadata-Version: 2.4
Name: ikpls
Version: 4.0.1
Summary: Improved Kernel PLS and Fast Cross-Validation.
License: Apache-2.0
License-File: LICENSE
Author: sm00thix
Author-email: oleemail@icloud.com
Maintainer: sm00thix
Maintainer-email: oleemail@icloud.com
Requires-Python: >=3.11,<3.15
Classifier: License :: OSI Approved :: Apache Software License
Classifier: Programming Language :: Python :: 3
Classifier: Programming Language :: Python :: 3.11
Classifier: Programming Language :: Python :: 3.12
Classifier: Programming Language :: Python :: 3.13
Classifier: Programming Language :: Python :: 3.14
Provides-Extra: jax
Requires-Dist: cvmatrix (>=3.0.0)
Requires-Dist: jax (>=0.5.0) ; extra == "jax"
Requires-Dist: jaxlib (>=0.5.0) ; extra == "jax"
Requires-Dist: joblib (>=1.3.2)
Requires-Dist: numpy (>=2.0.0)
Requires-Dist: scikit-learn (>=1.5.0)
Requires-Dist: tqdm (>=4.66.1)
Project-URL: Homepage, https://ikpls.readthedocs.io/en/latest/
Project-URL: Repository, https://github.com/sm00thix/ikpls
